tsvis/__init__.py
tsvis/logger/__init__.py
tsvis/logger/crc32c.py
tsvis/logger/onnx_graph.py
tsvis/logger/proto_graph.py
tsvis/logger/pytorch_graph.py
tsvis/logger/summary.py
tsvis/logger/summary_writer.py
tsvis/logger/utils.py
tsvis/logger/writer.py
tsvis/logger/x2num.py
tsvis/parser/__init__.py
tsvis/parser/log_parser.py
tsvis/parser/loader/__init__.py
tsvis/parser/loader/dictionary_watcher.py
tsvis/parser/loader/lazy_load.py
tsvis/parser/loader/logfile_loader.py
tsvis/parser/utils/__init__.py
tsvis/parser/utils/cache_io.py
tsvis/parser/utils/logfile_utils.py
tsvis/parser/utils/vis_logging.py
tsvis/parser/visparser/__init__.py
tsvis/parser/visparser/event_parser.py
tsvis/parser/visparser/events_reader.py
tsvis/parser/visparser/summary_reader.py
tsvis/proto/__init__.py
tsvis/proto/attr_value_pb2.py
tsvis/proto/event_pb2.py
tsvis/proto/graph_pb2.py
tsvis/proto/node_def_pb2.py
tsvis/proto/plugin_hparams_pb2.py
tsvis/proto/projector_pb2.py
tsvis/proto/step_stats_pb2.py
tsvis/proto/summary_pb2.py
tsvis/proto/tensor_pb2.py
tsvis/proto/types_pb2.py
tsvis/proto/versions_pb2.py
tsvis/server/__init__.py
tsvis/server/command_line.py
tsvis/server/main.py
tsvis/server/manage.py
tsvis/server/backend/__init__.py
tsvis/server/backend/asgi.py
tsvis/server/backend/settings.py
tsvis/server/backend/urls.py
tsvis/server/backend/wsgi.py
tsvis/server/backend/api/__init__.py
tsvis/server/backend/api/api.py
tsvis/server/backend/api/utils.py
tsvis/server/backend/component/__init__.py
tsvis/server/backend/component/Audio/__init__.py
tsvis/server/backend/component/Audio/audio_read.py
tsvis/server/backend/component/Audio/provider.py
tsvis/server/backend/component/Distribution/__init__.py
tsvis/server/backend/component/Distribution/dist_read.py
tsvis/server/backend/component/Distribution/provider.py
tsvis/server/backend/component/Exception/__init__.py
tsvis/server/backend/component/Exception/exception_read.py
tsvis/server/backend/component/Exception/histogram.py
tsvis-0.4.2.dist-info/LICENSE
tsvis-0.4.2.dist-info/METADATA
tsvis-0.4.2.dist-info/WHEEL
tsvis-0.4.2.dist-info/entry_points.txt
tsvis-0.4.2.dist-info/top_level.txt
tsvis-0.4.2.dist-info/RECORD
