Metadata-Version: 2.1
Name: tsvis
Version: 0.4.2
Summary: TS-VIS is a Python module for deep learning visualization
Home-page: UNKNOWN
Author: iGame
Author-email: igalab@163.com
License: Apache License
Platform: UNKNOWN
Requires-Dist: numpy
Requires-Dist: watchdog
Requires-Dist: tsne-mp (>=0.1.13)
Requires-Dist: crc32c (>=2.2)
Requires-Dist: Django (>=3.0.3)
Requires-Dist: Pillow
Requires-Dist: protobuf (>=3.15.8)
Requires-Dist: django-cors-headers (>=3.7.0)
Requires-Dist: soundfile (>=0.10.3)
